AUTHORS.rst
CONTRIBUTING.rst
LICENSE.md
MANIFEST.in
README.rst
setup.py
django_qa.egg-info/PKG-INFO
django_qa.egg-info/SOURCES.txt
django_qa.egg-info/dependency_links.txt
django_qa.egg-info/not-zip-safe
django_qa.egg-info/requires.txt
django_qa.egg-info/top_level.txt
qa/__init__.py
qa/admin.py
qa/apps.py
qa/forms.py
qa/mixins.py
qa/models.py
qa/signals.py
qa/urls.py
qa/utils.py
qa/views.py
qa/migrations/0001_initial.py
qa/migrations/0001_initial.pyc
qa/migrations/0002_auto_20160412_1336.py
qa/migrations/0002_auto_20160412_1336.pyc
qa/migrations/0003_auto_20160414_1413.py
qa/migrations/0003_auto_20160414_1413.pyc
qa/migrations/0004_answer_updated.py
qa/migrations/0004_answer_updated.pyc
qa/migrations/0005_auto_20160519_1057.py
qa/migrations/0005_auto_20160519_1057.pyc
qa/migrations/0006_question_total_points.py
qa/migrations/0006_question_total_points.pyc
qa/migrations/0007_answer_total_points.py
qa/migrations/0007_answer_total_points.pyc
qa/migrations/0008_auto_20160719_0729.py
qa/migrations/0008_auto_20160719_0729.pyc
qa/migrations/0009_auto_20160919_1528.py
qa/migrations/0009_auto_20160919_1528.pyc
qa/migrations/0010_auto_20160919_2033.py
qa/migrations/0010_auto_20160919_2033.pyc
qa/migrations/0011_question_slug.py
qa/migrations/0011_question_slug.pyc
qa/migrations/0012_remove_question_views.py
qa/migrations/0012_remove_question_views.pyc
qa/migrations/__init__.py
qa/migrations/__init__.pyc
qa/migrations/__pycache__/0001_initial.cpython-36.pyc
qa/migrations/__pycache__/0002_auto_20160412_1336.cpython-36.pyc
qa/migrations/__pycache__/0003_auto_20160414_1413.cpython-36.pyc
qa/migrations/__pycache__/0004_answer_updated.cpython-36.pyc
qa/migrations/__pycache__/0005_auto_20160519_1057.cpython-36.pyc
qa/migrations/__pycache__/0006_question_total_points.cpython-36.pyc
qa/migrations/__pycache__/0007_answer_total_points.cpython-36.pyc
qa/migrations/__pycache__/0008_auto_20160719_0729.cpython-36.pyc
qa/migrations/__pycache__/0009_auto_20160919_1528.cpython-36.pyc
qa/migrations/__pycache__/0010_auto_20160919_2033.cpython-36.pyc
qa/migrations/__pycache__/0011_question_slug.cpython-36.pyc
qa/migrations/__pycache__/0012_remove_question_views.cpython-36.pyc
